odoo10_addon_product_harmonized_system-10.0.1.0.0-py2.7-nspkg.pth
odoo/addons/product_harmonized_system/__manifest__.py
odoo/addons/product_harmonized_system/__init__.py
odoo/addons/product_harmonized_system/README.rst
odoo/addons/product_harmonized_system/security/product_hs_security.xml
odoo/addons/product_harmonized_system/security/ir.model.access.csv
odoo/addons/product_harmonized_system/models/product_template.py
odoo/addons/product_harmonized_system/models/__init__.py
odoo/addons/product_harmonized_system/models/hs_code.py
odoo/addons/product_harmonized_system/models/product_category.py
odoo/addons/product_harmonized_system/i18n/product_harmonized_system.pot
odoo/addons/product_harmonized_system/i18n/fr.po
odoo/addons/product_harmonized_system/views/hs_code.xml
odoo/addons/product_harmonized_system/views/product_category.xml
odoo/addons/product_harmonized_system/views/product_template.xml
odoo/addons/product_harmonized_system/demo/product_demo.xml
odoo10_addon_product_harmonized_system-10.0.1.0.0.dist-info/top_level.txt
odoo10_addon_product_harmonized_system-10.0.1.0.0.dist-info/WHEEL
odoo10_addon_product_harmonized_system-10.0.1.0.0.dist-info/RECORD
odoo10_addon_product_harmonized_system-10.0.1.0.0.dist-info/metadata.json
odoo10_addon_product_harmonized_system-10.0.1.0.0.dist-info/DESCRIPTION.rst
odoo10_addon_product_harmonized_system-10.0.1.0.0.dist-info/METADATA
odoo10_addon_product_harmonized_system-10.0.1.0.0.dist-info/namespace_packages.txt
